projgen/__init__.py
projgen/cli.py
projgen/core.py
projgen-0.2.dist-info/licenses/LICENSE
projgen-0.2.dist-info/METADATA
projgen-0.2.dist-info/WHEEL
projgen-0.2.dist-info/entry_points.txt
projgen-0.2.dist-info/top_level.txt
projgen-0.2.dist-info/RECORD
