Metadata-Version: 2.4
Name: projgen
Version: 0.2
Summary: A CLI tool to generate project structure from a JSON file
Author-email: Avinash Kumar Prajapati <aviavi61106@gmail.com>
License-Expression: MIT
Project-URL: Homepage, https://github.com/AvinashPrajapati/Python/tree/main/projgen
Project-URL: Repository, https://github.com/AvinashPrajapati/projgen/tree/main
Project-URL: Issues, https://github.com/AvinashPrajapati/projgen/issues
Requires-Python: >=3.7
License-File: LICENSE
Dynamic: license-file
